{
	"displayName": "Flint Chicken",
	"dropItem": "minecraft:flint",
	"dropItemNBT": "",
	"spawnNaturally": false,
	"spawnType": 1,
	"spawnWeight": 15,
	"canBreed": true,
	"baseHealth": 4,
	"baseSpeed": 0.25,
	"isFireImmune": false,
	"conversion": 250,
	"biomesWhitelist": ["minecraft:gravelly_mountains", "minecraft:modified_gravelly_mountains", "minecraft:stone_shore", "minecraft:mountains"],
	"biomesBlacklist": [],
	"eggLayTime": 6000,
	"eggColorBackground": 7039815,
	"eggColorForeground": 10724213,
	"hasTrait": 0,
	"parentA": "",
	"parentB": "",
	"enabled": true
}
